{
  "kind": "collectionType",
  "collectionName": "blog_categories",
  "info": {
    "singularName": "blog-category",
    "pluralName": "blog-categories",
    "displayName": "Blog Categories",
    "description": ""
  },
  "options": {
    "draftAndPublish": false
  },
  "pluginOptions": {},
  "attributes": {
    "name": {
      "type": "string",
      "required": true,
      "unique": true
    },
    "status": {
      "type": "boolean",
      "required": true,
      "default": true
    },
    "description": {
      "type": "text"
    },
    "slug": {
      "type": "uid",
      "targetField": "name",
      "required": true
    },
    "parent_category": {
      "type": "relation",
      "relation": "oneToOne",
      "target": "api::blog-category.blog-category"
    }
  }
}
