{
  "collectionName": "components_elements_reviews",
  "info": {
    "displayName": "Review",
    "icon": "star-half-alt",
    "description": ""
  },
  "options": {},
  "attributes": {
    "rating": {
      "type": "decimal",
      "required": false,
      "min": 0,
      "max": 5
    },
    "Type": {
      "type": "enumeration",
      "enum": [
        "customer",
        "inhouse"
      ],
      "required": true,
      "default": "customer"
    },
    "review": {
      "type": "text",
      "required": true
    }
  }
}
